hmlr_frontend_jinja/__init__.py
hmlr_frontend_jinja/templates/components/footer/macro.html
hmlr_frontend_jinja/templates/components/header/macro.html
hmlr_frontend_jinja-2.0.0.dist-info/LICENSE
hmlr_frontend_jinja-2.0.0.dist-info/METADATA
hmlr_frontend_jinja-2.0.0.dist-info/WHEEL
hmlr_frontend_jinja-2.0.0.dist-info/top_level.txt
hmlr_frontend_jinja-2.0.0.dist-info/RECORD
