Metadata-Version: 2.1
Name: hmlr-frontend-jinja
Version: 2.0.0
Summary: HMLR Frontend Jinja Macros
Home-page: https://github.com/LandRegistry/hmlr-frontend-jinja
Author: Matt Shaw
Author-email: matthew.shaw@landregistry.gov.uk
Classifier: Development Status :: 5 - Production/Stable
Classifier: Programming Language :: Python :: 3.8
Classifier: Programming Language :: Python :: 3.9
Classifier: Programming Language :: Python :: 3.10
Classifier: Programming Language :: Python :: 3.11
Classifier: Programming Language :: Python :: 3.12
Classifier: License :: OSI Approved :: MIT License
Classifier: Environment :: Web Environment
Classifier: Operating System :: OS Independent
Classifier: Intended Audience :: Developers
Classifier: Topic :: Software Development :: Code Generators
Classifier: Topic :: Software Development :: User Interfaces
Classifier: Topic :: Text Processing :: Markup :: HTML
Requires-Python: >=3.8
License-File: LICENSE
Requires-Dist: jinja2 !=3.0.0,!=3.0.1
